cez_distribuce_data_fetcher/__init__.py
cez_distribuce_data_fetcher/browsing.py
cez_distribuce_data_fetcher/logger.py
cez_distribuce_data_fetcher/main.py
cez_distribuce_data_fetcher/pnd.py
cez_distribuce_data_fetcher-0.0.2.dist-info/METADATA
cez_distribuce_data_fetcher-0.0.2.dist-info/WHEEL
cez_distribuce_data_fetcher-0.0.2.dist-info/RECORD
