Metadata-Version: 2.3
Name: cez-distribuce-data-fetcher
Version: 0.0.2
Summary: Fetches energy data from the CEZ Distribuce PND website
Author-email: aka-raccoon <42897550+aka-raccoon@users.noreply.github.com>
Requires-Python: >=3.11
Requires-Dist: selenium>=4.21.0
